cursory/__init__.py
cursory/cursory.py
cursory/py.typed
cursory/trajectories.json.gz
cursory/trajectory_selection.py
cursory-1.0.1.dist-info/licenses/LICENSE
cursory-1.0.1.dist-info/METADATA
cursory-1.0.1.dist-info/WHEEL
cursory-1.0.1.dist-info/top_level.txt
cursory-1.0.1.dist-info/RECORD
